pydataapi/__init__.py
pydataapi/dbapi.py
pydataapi/exceptions.py
pydataapi/pydataapi.py
pydataapi/version.py
pydataapi/dialect/__init__.py
pydataapi/dialect/base.py
pydataapi/dialect/mysql.py
pydataapi/dialect/postgresql.py
tests/__init__.py
tests/integration/__init__.py
tests/integration/docker-compose.yml
tests/integration/test_mysql.py
tests/pydataapi/__init__.py
tests/pydataapi/test_dbaapi.py
tests/pydataapi/test_dialect.py
tests/pydataapi/test_pydataapi.py
pydataapi-0.4.24.dist-info/LICENSE
pydataapi-0.4.24.dist-info/METADATA
pydataapi-0.4.24.dist-info/WHEEL
pydataapi-0.4.24.dist-info/entry_points.txt
pydataapi-0.4.24.dist-info/top_level.txt
pydataapi-0.4.24.dist-info/zip-safe
pydataapi-0.4.24.dist-info/RECORD
