Metadata-Version: 2.1
Name: pydataapi
Version: 0.4.24
Summary: py-data-api is a user-friendly client for AWS Aurora Serverless's Data API
Home-page: https://github.com/koxudaxi/py-data-api
Author: Koudai Aono
Author-email: koxudaxi@gmail.com
License: UNKNOWN
Platform: UNKNOWN
Classifier: Development Status :: 3 - Alpha
Classifier: Natural Language :: English
Classifier: License :: OSI Approved :: MIT License
Classifier: Programming Language :: Python :: 3
Classifier: Programming Language :: Python :: 3.6
Classifier: Programming Language :: Python :: 3.7
Classifier: Programming Language :: Python :: 3.8
Classifier: Programming Language :: Python :: Implementation :: CPython
Requires-Python: >=3.6.1
Requires-Dist: boto3 (<2,>=1.12.7)
Requires-Dist: SQLAlchemy (<1.4,>=1.3.13)
Requires-Dist: pydantic (<1.9,>=1.8)
Requires-Dist: more-itertools (<8.5,>=8.0.2)
Provides-Extra: all
Requires-Dist: pytest-runner ; extra == 'all'
Requires-Dist: setuptools-scm ; extra == 'all'
Requires-Dist: pytest ; extra == 'all'
Requires-Dist: pytest-benchmark ; extra == 'all'
Requires-Dist: pytest-cov ; extra == 'all'
Requires-Dist: pytest-mock ; extra == 'all'
Requires-Dist: pytest-docker-compose ; extra == 'all'
Requires-Dist: mypy ; extra == 'all'
Requires-Dist: black ; extra == 'all'
Requires-Dist: isort (>=5.0.7) ; extra == 'all'
Requires-Dist: PyMySQL ; extra == 'all'
Requires-Dist: docker-compose ; extra == 'all'
Requires-Dist: requests (==2.20.1) ; extra == 'all'
Requires-Dist: mkdocs ; extra == 'all'
Requires-Dist: mkdocs-material ; extra == 'all'
Requires-Dist: wheel ; extra == 'all'
Requires-Dist: twine ; extra == 'all'
Requires-Dist: codecov ; extra == 'all'
Provides-Extra: ci
Requires-Dist: codecov ; extra == 'ci'
Provides-Extra: docs
Requires-Dist: mkdocs ; extra == 'docs'
Requires-Dist: mkdocs-material ; extra == 'docs'
Provides-Extra: setup
Requires-Dist: pytest-runner ; extra == 'setup'
Requires-Dist: setuptools-scm ; extra == 'setup'
Provides-Extra: test
Requires-Dist: pytest ; extra == 'test'
Requires-Dist: pytest-benchmark ; extra == 'test'
Requires-Dist: pytest-cov ; extra == 'test'
Requires-Dist: pytest-mock ; extra == 'test'
Requires-Dist: pytest-docker-compose ; extra == 'test'
Requires-Dist: mypy ; extra == 'test'
Requires-Dist: black ; extra == 'test'
Requires-Dist: isort (>=5.0.7) ; extra == 'test'
Requires-Dist: PyMySQL ; extra == 'test'
Requires-Dist: docker-compose ; extra == 'test'
Requires-Dist: requests (==2.20.1) ; extra == 'test'
Provides-Extra: wheel
Requires-Dist: wheel ; extra == 'wheel'
Requires-Dist: twine ; extra == 'wheel'
